zking/__init__.py
zking/main.py
zking-0.3.dist-info/METADATA
zking-0.3.dist-info/WHEEL
zking-0.3.dist-info/top_level.txt
zking-0.3.dist-info/RECORD
