Metadata-Version: 2.1
Name: zking
Version: 0.3
